main.py
edge_tts_mcp-0.1.1.dist-info/licenses/LICENSE
edge_tts_mcp-0.1.1.dist-info/METADATA
edge_tts_mcp-0.1.1.dist-info/WHEEL
edge_tts_mcp-0.1.1.dist-info/entry_points.txt
edge_tts_mcp-0.1.1.dist-info/top_level.txt
edge_tts_mcp-0.1.1.dist-info/RECORD
