Metadata-Version: 2.4
Name: edge-tts-mcp
Version: 0.1.1
Summary: A Text-to-Speech (TTS) service based on Model Context Protocol (MCP), using Microsoft Edge TTS engine
Project-URL: Homepage, https://github.com/eraincc/edge-tts-mcp
Project-URL: Issues, https://github.com/eraincc/edge-tts-mcp/issues
Requires-Python: >=3.11
License-File: LICENSE
Requires-Dist: mcp[cli]>=1.9.3
Requires-Dist: edge-tts==7.0.2
Requires-Dist: nest-asyncio==1.6.0
Dynamic: license-file
